swauth/__init__.py
swauth/authtypes.py
swauth/middleware.py
swauth/swift_version.py
swauth-1.3.0.data/scripts/swauth-add-account
swauth-1.3.0.data/scripts/swauth-add-user
swauth-1.3.0.data/scripts/swauth-cleanup-tokens
swauth-1.3.0.data/scripts/swauth-delete-account
swauth-1.3.0.data/scripts/swauth-delete-user
swauth-1.3.0.data/scripts/swauth-list
swauth-1.3.0.data/scripts/swauth-prep
swauth-1.3.0.data/scripts/swauth-set-account-service
swauth-1.3.0.dist-info/DESCRIPTION.rst
swauth-1.3.0.dist-info/METADATA
swauth-1.3.0.dist-info/RECORD
swauth-1.3.0.dist-info/WHEEL
swauth-1.3.0.dist-info/entry_points.txt
swauth-1.3.0.dist-info/metadata.json
swauth-1.3.0.dist-info/pbr.json
swauth-1.3.0.dist-info/top_level.txt
