Metadata-Version: 2.0
Name: swauth
Version: 1.3.0
Summary: An alternative authentication system for Swift
Home-page: https://github.com/openstack/swauth
Author: OpenStack
Author-email: openstack-dev@lists.openstack.org
License: UNKNOWN
Platform: UNKNOWN
Classifier: Development Status :: 5 - Production/Stable
Classifier: Environment :: OpenStack
Classifier: Intended Audience :: Information Technology
Classifier: Intended Audience :: System Administrators
Classifier: License :: OSI Approved :: Apache Software License
Classifier: Operating System :: POSIX :: Linux
Classifier: Programming Language :: Python
Classifier: Programming Language :: Python :: 2
Classifier: Programming Language :: Python :: 2.7
Requires-Dist: eventlet (!=0.18.3,!=0.20.1,<0.21.0,>=0.18.2)
Requires-Dist: python-swiftclient (>=3.2.0)
Requires-Dist: six (>=1.10.0)
